flick.py
flick-0.1.dist-info/WHEEL
flick-0.1.dist-info/METADATA
flick-0.1.dist-info/RECORD
