Metadata-Version: 2.1
Name: flick
Version: 0.1
Summary: flick: watch for something not so special
Home-page: https://github.com/okken/flick
License: UNKNOWN
Author: Brian Okken
Author-email: 
